Metadata-Version: 2.1
Name: tabledataextractor
Version: 1.5.11
Summary: Extracts data from tables
Home-page: https://www.tabledataextractor.com
Author: Juraj Mavračić
Author-email: jm2111@cam.ac.uk
License: MIT License
Platform: UNKNOWN
License-File: LICENSE
